LICENSE
MANIFEST.in
README.md
pyproject.toml
requirements.txt
requirements_dev.txt
setup.cfg
setup.py
mighty_bedmas_calculator/__init__.py
mighty_bedmas_calculator/_cli.py
mighty_bedmas_calculator/infix_evaluator.py
mighty_bedmas_calculator/operator.py
mighty_bedmas_calculator.egg-info/PKG-INFO
mighty_bedmas_calculator.egg-info/SOURCES.txt
mighty_bedmas_calculator.egg-info/dependency_links.txt
mighty_bedmas_calculator.egg-info/entry_points.txt
mighty_bedmas_calculator.egg-info/not-zip-safe
mighty_bedmas_calculator.egg-info/requires.txt
mighty_bedmas_calculator.egg-info/top_level.txt
tests/test_infix_evaluator.py