Metadata-Version: 2.1
Name: mighty-bedmas-calculator
Version: 2022.7.26.0
Summary: Calculate string infix expressions following BEDMAS.
Home-page: https://github.com/jdboisvert/mightly-bedmas-calculator
Author: Jeffrey Boisvert
Author-email: info.jeffreyboisvert@gmail.com
License: MIT License
Download-URL: https://github.com/jdboisvert/mightly-bedmas-calculator/archive/refs/tags/v2022.7.26.0.zip
Project-URL: Repository, https://github.com/jdboisvert/mightly-bedmas-calculator
Project-URL: Bug Reports, https://github.com/jdboisvert/mightly-bedmas-calculator/issues
Platform: any
Classifier: Development Status :: 3 - Alpha
Classifier: Intended Audience :: Developers
Classifier: License :: OSI Approved :: MIT License
Classifier: Operating System :: OS Independent
Classifier: Programming Language :: Python :: 3.8
Classifier: Programming Language :: Python :: 3.9
Classifier: Programming Language :: Python :: 3.10
Requires-Python: >=3.8.0
License-File: LICENSE
